neo4j/__init__.py
neo4j/_api.py
neo4j/_auth_management.py
neo4j/_conf.py
neo4j/_data.py
neo4j/_deadline.py
neo4j/_exceptions.py
neo4j/_meta.py
neo4j/_routing.py
neo4j/addressing.py
neo4j/api.py
neo4j/auth_management.py
neo4j/conf.py
neo4j/data.py
neo4j/debug.py
neo4j/exceptions.py
neo4j/meta.py
neo4j/packstream.py
neo4j/py.typed
neo4j/routing.py
neo4j/warnings.py
neo4j/_async/__init__.py
neo4j/_async/auth_management.py
neo4j/_async/bookmark_manager.py
neo4j/_async/config.py
neo4j/_async/driver.py
neo4j/_async/home_db_cache.py
neo4j/_async/_debug/__init__.py
neo4j/_async/_debug/_concurrency_check.py
neo4j/_async/io/__init__.py
neo4j/_async/io/_bolt.py
neo4j/_async/io/_bolt3.py
neo4j/_async/io/_bolt4.py
neo4j/_async/io/_bolt5.py
neo4j/_async/io/_bolt_socket.py
neo4j/_async/io/_common.py
neo4j/_async/io/_pool.py
neo4j/_async/work/__init__.py
neo4j/_async/work/result.py
neo4j/_async/work/session.py
neo4j/_async/work/transaction.py
neo4j/_async/work/workspace.py
neo4j/_async_compat/__init__.py
neo4j/_async_compat/concurrency.py
neo4j/_async_compat/util.py
neo4j/_async_compat/network/__init__.py
neo4j/_async_compat/network/_bolt_socket.py
neo4j/_async_compat/network/_util.py
neo4j/_async_compat/shims/__init__.py
neo4j/_codec/__init__.py
neo4j/_codec/hydration/__init__.py
neo4j/_codec/hydration/_common.py
neo4j/_codec/hydration/_interface/__init__.py
neo4j/_codec/hydration/v1/__init__.py
neo4j/_codec/hydration/v1/hydration_handler.py
neo4j/_codec/hydration/v1/spatial.py
neo4j/_codec/hydration/v1/temporal.py
neo4j/_codec/hydration/v2/__init__.py
neo4j/_codec/hydration/v2/hydration_handler.py
neo4j/_codec/hydration/v2/temporal.py
neo4j/_codec/packstream/__init__.py
neo4j/_codec/packstream/_common.py
neo4j/_codec/packstream/_python/__init__.py
neo4j/_codec/packstream/_python/_common.py
neo4j/_codec/packstream/v1/__init__.py
neo4j/_codec/packstream/v1/types.py
neo4j/_debug/__init__.py
neo4j/_debug/_config.py
neo4j/_debug/_notification_printer.py
neo4j_driver-5.28.2.dist-info/licenses/LICENSE.APACHE2.txt
neo4j_driver-5.28.2.dist-info/licenses/LICENSE.PYTHON.txt
neo4j_driver-5.28.2.dist-info/licenses/LICENSE.txt
neo4j_driver-5.28.2.dist-info/licenses/NOTICE.txt
neo4j_driver-5.28.2.dist-info/METADATA
neo4j_driver-5.28.2.dist-info/WHEEL
neo4j_driver-5.28.2.dist-info/top_level.txt
neo4j_driver-5.28.2.dist-info/RECORD
