Metadata-Version: 2.4
Name: neo4j-driver
Version: 5.28.2
Summary: Neo4j Bolt driver for Python
Author-email: "Neo4j, Inc." <drivers@neo4j.com>
License: Apache License, Version 2.0
Project-URL: Homepage, https://neo4j.com/
Project-URL: Repository, https://github.com/neo4j/neo4j-python-driver
Project-URL: Docs (Manual), https://neo4j.com/docs/python-manual/current/
Project-URL: Docs (API Reference), https://neo4j.com/docs/api/python-driver/current/
Project-URL: Issue Tracker, https://github.com/neo4j/neo4j-python-driver/issues
Project-URL: Changelog, https://github.com/neo4j/neo4j-python-driver/wiki
Project-URL: Forum, https://community.neo4j.com/c/drivers-stacks/python/
Project-URL: Discord, https://discord.com/invite/neo4j
Keywords: neo4j,graph,database
Classifier: Development Status :: 5 - Production/Stable
Classifier: Framework :: AsyncIO
Classifier: Intended Audience :: Developers
Classifier: License :: OSI Approved :: Apache Software License
Classifier: Operating System :: OS Independent
Classifier: Programming Language :: Python :: 3.7
Classifier: Programming Language :: Python :: 3.8
Classifier: Programming Language :: Python :: 3.9
Classifier: Programming Language :: Python :: 3.10
Classifier: Programming Language :: Python :: 3.11
Classifier: Programming Language :: Python :: 3.12
Classifier: Programming Language :: Python :: 3.13
Classifier: Topic :: Database
Classifier: Topic :: Software Development
Classifier: Typing :: Typed
Requires-Python: >=3.7
License-File: LICENSE.APACHE2.txt
License-File: LICENSE.PYTHON.txt
License-File: LICENSE.txt
License-File: NOTICE.txt
Requires-Dist: pytz
Provides-Extra: numpy
Requires-Dist: numpy<3.0.0,>=1.7.0; extra == "numpy"
Provides-Extra: pandas
Requires-Dist: pandas<3.0.0,>=1.1.0; extra == "pandas"
Requires-Dist: numpy<3.0.0,>=1.7.0; extra == "pandas"
Provides-Extra: pyarrow
Requires-Dist: pyarrow>=1.0.0; extra == "pyarrow"
Dynamic: description
Dynamic: license-file
